{
    "KR": [
        {
            "1":"#77C4A3",
            "2":"#F5A200",
            "3":"#003DA5",
            "4":"#0C8E72",
            "K":"#204080",
            "I":"#505457",
            "IS":"#C30E2F",
            "IC":"#1CAE4C",
            "S":"#5288F5",
            "M":"#E06040",
            "N":"#3D99C2",
            "T":"#80E080",
            "O":"#3D860B",
            "V":"#3698D2",
            "ST":"#074286",
            "D":"#1D2A56",
            "A":"#753778",
            "W":"#F9BE00"
        }
    ],
    "SM": [
        {
            "1":"#0052A4",
            "2":"#009D3E",
            "3":"#EF7C1C",
            "4":"#00A5DE",
            "5":"#996CAC",
            "6":"#CD7C2F",
            "7":"#747F00",
            "8":"#EA545D"
        }
    ],
    "S9": [
        {
            "9":"#BDB092"
        }
    ],
    "GG": [
        {
            "G":"#A17800"
        }
    ],
    "UI": [
        {
            "U":"#B0CE18"
        }
    ],
    "SW": [
        {
            "S":"#81A914"
        }
    ],
    "IM": [
        {
            "1":"#7CA8D5",
            "2":"#ED8B00",
            "M":"#FFCD12"
        }
    ],
    "KA": [
        {
            "A":"#0090D2",
            "J":"#F97600"
        }
    ]
}